setup.py
Products/StickyList
Products/__init__.py
Products.StickyList.egg-info/PKG-INFO
Products.StickyList.egg-info/SOURCES.txt
Products.StickyList.egg-info/SOURCES.txt~
Products.StickyList.egg-info/dependency_links.txt
Products.StickyList.egg-info/entry_points.txt
Products.StickyList.egg-info/namespace_packages.txt
Products.StickyList.egg-info/not-zip-safe
Products.StickyList.egg-info/requires.txt
Products.StickyList.egg-info/top_level.txt
Products/StickyList/StickyList
Products/StickyList/__init__.py
Products/StickyList/changes.txt
Products/StickyList/config.py
Products/StickyList/configure.zcml
Products/StickyList/profiles
Products/StickyList/profiles.zcml
Products/StickyList/readme.txt
Products/StickyList/refresh.txt
Products/StickyList/setuphandlers.py
Products/StickyList/skins
Products/StickyList/version.txt
Products/StickyList/StickyList/StickyList.py
Products/StickyList/StickyList/__init__.py
Products/StickyList/StickyList/interfaces.py
Products/StickyList/profiles/default
Products/StickyList/profiles/default/StickyList_marker.txt
Products/StickyList/profiles/default/cssregistry.xml
Products/StickyList/profiles/default/factorytool.xml
Products/StickyList/profiles/default/import_steps.xml
Products/StickyList/profiles/default/jsregistry.xml
Products/StickyList/profiles/default/metadata.xml
Products/StickyList/profiles/default/skins.xml
Products/StickyList/profiles/default/types
Products/StickyList/profiles/default/types.xml
Products/StickyList/profiles/default/types/StickyList.xml
Products/StickyList/skins/stickylist_images
Products/StickyList/skins/stickylist_templates
Products/StickyList/skins/stickylist_images/StickyList.gif
Products/StickyList/skins/stickylist_templates/stickylist_macros.pt