Metadata-Version: 1.0
Name: Products.StickyList
Version: 1.0a
Summary: Enables selecting a number of items and storing that selection.
Home-page: http://www.nidelven-it.no/d
Author: Morten W. Petersen
Author-email: info@nidelven-it.no
License: GPL
Keywords: python plone archetypes presentation
Platform: UNKNOWN
Classifier: Programming Language :: Python
Classifier: Framework :: Plone
